setup.py
handbag/__init__.py
handbag/cursor.py
handbag/database.py
handbag/dson.py
handbag/environment.py
handbag/index.py
handbag/model.py
handbag/model_adaptors.py
handbag/registry.py
handbag/relationships.py
handbag/table.py
handbag/transaction.py
handbag/uniqueid.py
handbag/validators.py
handbag/version.py
handbag.egg-info/PKG-INFO
handbag.egg-info/SOURCES.txt
handbag.egg-info/dependency_links.txt
handbag.egg-info/requires.txt
handbag.egg-info/top_level.txt
handbag/dbm/__init__.py
handbag/dbm/abstract.py
handbag/dbm/lmdbdbm.py
tests/__init__.py
tests/test_cursor.py
tests/test_index.py
tests/test_model.py
tests/test_relationships.py
tests/test_table.py
tests/test_validators.py