Metadata-Version: 1.0
Name: handbag
Version: 0.1.8
Summary: An embedded database and data modeling library for python.
Home-page: https://github.com/elishacook/handbag
Author: Elisha Fitch-Cook
Author-email: elisha@elishacook.com
License: UNKNOWN
Platform: UNKNOWN
